{
  "blogs": [
    {
      "title": "My New Website",
      "body": "This is my new website",
      "author": "Yusuf",
      "avatar": "https://i.ibb.co/PxkfQPX/github-avatar.png",
      "id": 1
    },
    {
      "title": "Welcome to My Web",
      "body": "My web is from React",
      "author": "Rizal",
      "avatar": "https://i.ibb.co/PxkfQPX/github-avatar.png",
      "id": 2
    },
    {
      "title": "Web Development with React",
      "body": "Learn React from the scratch",
      "author": "Yusuf",
      "avatar": "https://i.ibb.co/PxkfQPX/github-avatar.png",
      "id": 3
    },
    {
      "title": "React.js Top Tips",
      "body": "React is so easy",
      "author": "Rizal",
      "avatar": "https://i.ibb.co/PxkfQPX/github-avatar.png",
      "id": 4
    },
    {
      "title": "React Hook",
      "body": "Learn React Hook with useState",
      "author": "James",
      "avatar": "https://i.ibb.co/PxkfQPX/github-avatar.png",
      "id": 5
    },
    {
      "title": "React Fetch Data",
      "body": "Fetch data from json-server",
      "author": "Rizal",
      "avatar": "https://i.ibb.co/PxkfQPX/github-avatar.png",
      "id": 6
    },
    {
      "title": "Blog terbaru",
      "body": "Lorem ipsum dolor sit amet, consectetur adipiscing elit, sed do eiusmod tempor incididunt ut labore et dolore magna aliqua. Diam quis enim lobortis scelerisque fermentum. Lorem dolor sed viverra ipsum. Condimentum vitae sapien pellentesque habitant morbi tristique. Bibendum at varius vel pharetra vel turpis. Vitae purus faucibus ornare suspendisse sed. Felis bibendum ut tristique et egestas. Sapien pellentesque habitant morbi tristique senectus et netus et malesuada. Non enim praesent elementum facilisis. Adipiscing diam donec adipiscing tristique risus nec feugiat. Dignissim sodales ut eu sem. Ipsum consequat nisl vel pretium lectus. Dui vivamus arcu felis bibendum ut tristique. Sit amet volutpat consequat mauris nunc congue nisi vitae. Sodales ut eu sem integer. Sit amet venenatis urna cursus eget nunc scelerisque viverra.",
      "author": "Yusuf",
      "id": 7
    },
    {
      "title": "Post new blog",
      "body": "Mattis pellentesque id nibh tortor id aliquet lectus proin nibh. Volutpat ac tincidunt vitae semper quis lectus nulla at. Lobortis mattis aliquam faucibus purus in massa tempor nec. Nulla aliquet porttitor lacus luctus accumsan tortor posuere. At volutpat diam ut venenatis. Phasellus vestibulum lorem sed risus ultricies tristique. Praesent semper feugiat nibh sed pulvinar. Vitae sapien pellentesque habitant morbi tristique senectus et. Justo eget magna fermentum iaculis eu non diam phasellus. Scelerisque eu ultrices vitae auctor eu augue ut lectus. Scelerisque felis imperdiet proin fermentum leo vel orci porta.",
      "author": "Rizal",
      "id": 8
    },
    {
      "title": "React-router History",
      "body": "Membuat redirect dengan react-router history",
      "author": "Yusuf",
      "id": 9
    }
  ]
}